pai/__init__.py
pai/__main__.py
pai/cli.py
pai/embed.py
pai/utils/option_choices.py
phenomic_ai-0.1.11.dist-info/LICENSE
phenomic_ai-0.1.11.dist-info/METADATA
phenomic_ai-0.1.11.dist-info/WHEEL
phenomic_ai-0.1.11.dist-info/entry_points.txt
phenomic_ai-0.1.11.dist-info/top_level.txt
phenomic_ai-0.1.11.dist-info/RECORD
