Metadata-Version: 2.1
Name: phenomic-ai
Version: 0.1.11
Summary: A CLI package which facilitates computational biologists with a single cell RNA embedding tool
Author-email: Phenomic AI <sctx@phenomic.ai>
License: Copyright 2024 Phenomic AI
Classifier: Development Status :: 4 - Beta
Classifier: Intended Audience :: Developers
Classifier: Intended Audience :: Information Technology
Classifier: Intended Audience :: Science/Research
Classifier: Topic :: Scientific/Engineering :: Bio-Informatics
Classifier: Operating System :: POSIX :: Linux
Classifier: Operating System :: MacOS :: MacOS X
Classifier: Programming Language :: Python
License-File: LICENSE
Requires-Dist: requests
Provides-Extra: dev
Requires-Dist: black ; extra == 'dev'
Requires-Dist: pytest ; extra == 'dev'
Requires-Dist: pytest-cov ; extra == 'dev'
